uib_experiments/__init__.py
uib_experiments/decorator.py
uib_experiments/data/__init__.py
uib_experiments/data/dades.py
uib_experiments/database_model/__init__.py
uib_experiments/database_model/database.py
uib_experiments/experiment/__init__.py
uib_experiments/experiment/experiment.py
uib_experiments/keras/__init__.py
uib_experiments/keras/telegramCallback.py
uib_experiments-1.6.1.dist-info/LICENSE
uib_experiments-1.6.1.dist-info/METADATA
uib_experiments-1.6.1.dist-info/WHEEL
uib_experiments-1.6.1.dist-info/top_level.txt
uib_experiments-1.6.1.dist-info/RECORD
