Metadata-Version: 2.1
Name: uib-experiments
Version: 1.6.1
Summary: Handle the experiments.
Home-page: https://github.com/miquelmn/uib_experiments
Download-URL: https://github.com/miquelmn/uib_experiments/archive/refs/tags/v0.9.2.tar.gz
Author: Miquel Miró Nicolau, Dr. Gabriel Moyà Alcover
Author-email: miquel.miro@uib.cat, gabriel_moya@uib.es
License-File: LICENSE
Requires-Dist: telegram-send
Requires-Dist: opencv-python
Requires-Dist: matplotlib
Requires-Dist: scipy
Requires-Dist: numpy
Requires-Dist: peewee
